rysk_client/__init__.py
rysk_client/cli.py
rysk_client/client.py
rysk_client/packages/eightballer/contracts/beyond_pricer/__init__.py
rysk_client/packages/eightballer/contracts/beyond_pricer/build/beyond_pricer.json
rysk_client/packages/eightballer/contracts/beyond_pricer/contract.py
rysk_client/packages/eightballer/contracts/beyond_pricer/contract.yaml
rysk_client/packages/eightballer/contracts/d_h_v_lens/__init__.py
rysk_client/packages/eightballer/contracts/d_h_v_lens/build/d_h_v_lens.json
rysk_client/packages/eightballer/contracts/d_h_v_lens/contract.py
rysk_client/packages/eightballer/contracts/d_h_v_lens/contract.yaml
rysk_client/packages/eightballer/contracts/o_token/__init__.py
rysk_client/packages/eightballer/contracts/o_token/build/o_token.json
rysk_client/packages/eightballer/contracts/o_token/contract.py
rysk_client/packages/eightballer/contracts/o_token/contract.yaml
rysk_client/packages/eightballer/contracts/option_exchange/__init__.py
rysk_client/packages/eightballer/contracts/option_exchange/build/option_exchange.json
rysk_client/packages/eightballer/contracts/option_exchange/contract.py
rysk_client/packages/eightballer/contracts/option_exchange/contract.yaml
rysk_client/packages/eightballer/contracts/opyn_controller/__init__.py
rysk_client/packages/eightballer/contracts/opyn_controller/build/opyn_controller.json
rysk_client/packages/eightballer/contracts/opyn_controller/contract.py
rysk_client/packages/eightballer/contracts/opyn_controller/contract.yaml
rysk_client/packages/eightballer/contracts/opyn_option_registry/__init__.py
rysk_client/packages/eightballer/contracts/opyn_option_registry/build/opyn_option_registry.json
rysk_client/packages/eightballer/contracts/opyn_option_registry/contract.py
rysk_client/packages/eightballer/contracts/opyn_option_registry/contract.yaml
rysk_client/packages/eightballer/contracts/usdc/__init__.py
rysk_client/packages/eightballer/contracts/usdc/build/usdc.json
rysk_client-0.2.17.dist-info/METADATA
rysk_client-0.2.17.dist-info/WHEEL
rysk_client-0.2.17.dist-info/entry_points.txt
rysk_client-0.2.17.dist-info/RECORD
