Metadata-Version: 2.1
Name: rysk_client
Version: 0.2.17
Summary: 
Author: 8baller
Author-email: 8ball030@gmail.com
Requires-Python: >=3.8,<=3.11
Classifier: Programming Language :: Python :: 3
Classifier: Programming Language :: Python :: 3.8
Classifier: Programming Language :: Python :: 3.9
Classifier: Programming Language :: Python :: 3.10
Classifier: Programming Language :: Python :: 3.11
Requires-Dist: python-dotenv (>=0.14.0,<0.18.0)
Requires-Dist: pyyaml (==5.3.1)
Requires-Dist: rich-click (>=1.6.1,<2.0.0)
Requires-Dist: web3 (>=5,<6)
Requires-Dist: websocket-client (>=0.32.0,<2)
